polishify/__init__.py
polishify/extract.py
polishify/polishify.py
polishify/static/__init__.py
polishify/static/dataset.json
polishify-0.1.0.dist-info/LICENSE
polishify-0.1.0.dist-info/METADATA
polishify-0.1.0.dist-info/WHEEL
polishify-0.1.0.dist-info/entry_points.txt
polishify-0.1.0.dist-info/top_level.txt
polishify-0.1.0.dist-info/RECORD
