Metadata-Version: 2.1
Name: polishify
Version: 0.1.0
Summary: Helps you convert Polish text of unknown encoding into UTF-8
Home-page: https://github.com/marekyggdrasil/polishify
Author: Marek Narozniak
Author-email: marek.yggdrasil@gmail.com
License: MIT
Classifier: Programming Language :: Python :: 3
Classifier: Programming Language :: Python :: 2
Classifier: License :: OSI Approved :: MIT License
Classifier: Operating System :: OS Independent
License-File: LICENSE
Requires-Dist: argparse
